src/__init__.py
src/main.py
pip_update_interactive-0.0.1.dist-info/LICENSE
pip_update_interactive-0.0.1.dist-info/METADATA
pip_update_interactive-0.0.1.dist-info/WHEEL
pip_update_interactive-0.0.1.dist-info/top_level.txt
pip_update_interactive-0.0.1.dist-info/RECORD
