Metadata-Version: 2.1
Name: pip-update-interactive
Version: 0.0.1
Summary: Simple interactive Package Manager
Author: Veldhaenchen (Johannes Velde)
Author-email: <jo.velde@gmx.de>
Keywords: python,pip,update,interactive
Classifier: Development Status :: 1 - Planning
Classifier: Intended Audience :: Developers
Classifier: Programming Language :: Python :: 3
Classifier: Operating System :: Unix
Classifier: Operating System :: MacOS :: MacOS X
Classifier: Operating System :: Microsoft :: Windows
License-File: LICENSE
